cli/__init__.py
cli/cli.py
mortgagemodeler/__init__.py
mortgagemodeler/amortizer.py
mortgagemodeler/loan.py
mortgagemodeler/utils/__init__.py
mortgagemodeler/utils/analytics.py
mortgagemodeler/utils/breakeven.py
mortgagemodeler/utils/cost_savings.py
mortgagemodeler/utils/curtailments.py
mortgagemodeler/utils/date.py
mortgagemodeler/utils/effective_apr.py
mortgagemodeler/utils/exta_payment_compare.py
mortgagemodeler/utils/interest.py
mortgagemodeler/utils/macro.py
mortgagemodeler/utils/plot_amortization.py
mortgagemodeler/utils/plotting.py
mortgagemodeler/utils/rates.py
mortgagemodeler/utils/summary_metrics.py
mortgagemodeler-0.4.3.dist-info/METADATA
mortgagemodeler-0.4.3.dist-info/WHEEL
mortgagemodeler-0.4.3.dist-info/entry_points.txt
mortgagemodeler-0.4.3.dist-info/top_level.txt
mortgagemodeler-0.4.3.dist-info/RECORD
